reportlab_typesetting/__init__.py
reportlab_typesetting/alignment.py
reportlab_typesetting/datatypes.py
reportlab_typesetting/engine.py
reportlab_typesetting/renderers.py
reportlab_typesetting-0.0.4.dist-info/licenses/LICENSE
reportlab_typesetting-0.0.4.dist-info/METADATA
reportlab_typesetting-0.0.4.dist-info/WHEEL
reportlab_typesetting-0.0.4.dist-info/top_level.txt
reportlab_typesetting-0.0.4.dist-info/RECORD
