Metadata-Version: 2.4
Name: reportlab_typesetting
Version: 0.0.4
Summary: A library to simplify complex typesetting with ReportLab, featuring Japanese Kinsoku rules, automatic font switching, and block alignment.
Author-email: T0date <47016429+T0date@users.noreply.github.com>
Project-URL: Homepage, https://github.com/T0date/reportlab_typesetting
Project-URL: Bug Tracker, https://github.com/T0date/reportlab_typesetting/issues
Classifier: Development Status :: 3 - Alpha
Classifier: License :: OSI Approved :: MIT License
Classifier: Natural Language :: Japanese
Classifier: Operating System :: OS Independent
Classifier: Programming Language :: Python :: 3
Classifier: Programming Language :: Python :: 3.11
Classifier: Programming Language :: Python :: 3.12
Classifier: Programming Language :: Python :: 3.13
Classifier: Topic :: Printing
Classifier: Topic :: Text Processing
Requires-Python: >=3.11
License-File: LICENSE
Requires-Dist: reportlab~=4.4
Requires-Dist: pyphen~=0.17
Provides-Extra: dev
Requires-Dist: pytest; extra == "dev"
Dynamic: license-file
